asgi/__init__.py
asgi/main.py
asgi/test.py
mercury/__init__.py
mercury/conf/__init__.py
mercury/conf/global_settings.py
mercury/core/application/__init__.py
mercury/core/exception.py
mercury/core/management/__init__.py
mercury/core/management/base.py
mercury/core/management/color.py
mercury/core/management/command/__init__.py
mercury/core/management/command/runasgi.py
mercury/core/management/command/runself.py
mercury/core/management/command/runwsgi.py
mercury/core/management/command/startapp.py
mercury/core/management/command/startproject.py
mercury/core/management/template.py
mercury/core/request/__init__.py
mercury/core/route/__init__.py
mercury/core/server/__init__.py
mercury/core/server/base.py
mercury/core/server/config.py
mercury/core/server/handler.py
mercury/core/server/lifespan/__init__.py
mercury/core/server/lifespan/off.py
mercury/core/server/lifespan/on.py
mercury/core/server/loop/__init__.py
mercury/core/server/middleware/__init__.py
mercury/core/server/middleware/asgi2.py
mercury/core/server/middleware/debug.py
mercury/core/server/middleware/wsgi.py
mercury/core/server/protocol/__init__.py
mercury/core/server/protocol/http/__init__.py
mercury/core/server/protocol/http/base.py
mercury/core/server/protocol/http/flow_control.py
mercury/core/server/protocol/http/parser/__init__.py
mercury/core/server/protocol/utils.py
mercury/core/server/server.py
mercury/core/view/__init__.py
mercury/core/view/base.py
mercury/core/view/viewset.py
mercury/db/__init__.py
mercury/template/app_template/__init__.py-tpl
mercury/template/app_template/admin.py-tpl
mercury/template/app_template/app.py-tpl
mercury/template/app_template/models.py-tpl
mercury/template/app_template/serializers.py-tpl
mercury/template/app_template/tests.py-tpl
mercury/template/app_template/views.py-tpl
mercury/template/project_template/.gitignore
mercury/template/project_template/main/__init__.py-tpl
mercury/template/project_template/main/setting.py-tpl
planet_mercury-0.0.2.dist-info/entry_points.txt
planet_mercury-0.0.2.dist-info/WHEEL
planet_mercury-0.0.2.dist-info/METADATA
planet_mercury-0.0.2.dist-info/license_files/LICENSE
planet_mercury-0.0.2.dist-info/RECORD
