Metadata-Version: 2.1
Name: planet-mercury
Version: 0.0.2
Summary: A python ASGI framework in planets plan project.
License: MIT
Author-email: RyomaHan <ryomahan1996@gmail.com>
Requires-Python: >=3.9
